micro_service_russ/__init__.py
micro_service_russ/main.py
micro_service_russ-0.1.0.dist-info/METADATA
micro_service_russ-0.1.0.dist-info/WHEEL
micro_service_russ-0.1.0.dist-info/RECORD
