Metadata-Version: 2.1
Name: micro-service-russ
Version: 0.1.0
Summary: This is package is not meant to be used in prod
Author: Rustam Mustafoev
Requires-Python: >=3.9,<4.0
Classifier: Programming Language :: Python :: 3
Classifier: Programming Language :: Python :: 3.9
Classifier: Programming Language :: Python :: 3.10
Classifier: Programming Language :: Python :: 3.11
Classifier: Programming Language :: Python :: 3.12
Requires-Dist: build (>=1.2.1,<2.0.0)
Requires-Dist: fastapi (>=0.110.1,<0.111.0)
Requires-Dist: pip (>=24.0,<25.0)
Requires-Dist: uvicorn (>=0.29.0,<0.30.0)
Requires-Dist: wheel (>=0.43.0,<0.44.0)
